SurveyAnalyzer/SurveyAnalyzer.py
SurveyAnalyzer/__init__.py
surveyanalyzer-1.3.1.dist-info/METADATA
surveyanalyzer-1.3.1.dist-info/WHEEL
surveyanalyzer-1.3.1.dist-info/top_level.txt
surveyanalyzer-1.3.1.dist-info/RECORD
