Metadata-Version: 2.1
Name: surveyanalyzer
Version: 1.3.1
Summary: A simple Comment Classification Tools
Home-page: https://github.com/lupin-oomura/SurveyAnalyzer.git
Author: Shin Oomura
Author-email: shin.oomura@gmail.com
Requires-Dist: openai
Requires-Dist: python-dotenv
Requires-Dist: numpy
Requires-Dist: scikit-learn
Requires-Dist: matplotlib
Requires-Dist: wordcloud
Requires-Dist: jaconv
Requires-Dist: mecab-python3
